{
  "main": {
    "id": "dde55e8015ea0b3c",
    "type": "split",
    "children": [
      {
        "id": "01628b8ee5a9114e",
        "type": "tabs",
        "children": [
          {
            "id": "e8acf4099b7af3fd",
            "type": "leaf",
            "state": {
              "type": "pdf",
              "state": {
                "file": "006 References/ALevel-CS.pdf"
              }
            }
          }
        ]
      }
    ],
    "direction": "vertical"
  },
  "left": {
    "id": "583c7194f7c8d673",
    "type": "mobile-drawer",
    "children": [
      {
        "id": "7d653e3784afe94e",
        "type": "leaf",
        "state": {
          "type": "file-explorer",
          "state": {
            "sortOrder": "alphabetical"
          }
        }
      },
      {
        "id": "41efd692a2b8a8b2",
        "type": "leaf",
        "state": {
          "type": "search",
          "state": {
            "query": "",
            "matchingCase": false,
            "explainSearch": false,
            "collapseAll": false,
            "extraContext": false,
            "sortOrder": "alphabetical"
          }
        }
      },
      {
        "id": "a2c9d06ce359b7ca",
        "type": "leaf",
        "state": {
          "type": "tag",
          "state": {
            "sortOrder": "frequency",
            "useHierarchy": true
          }
        }
      },
      {
        "id": "58d06a8938d9b8ab",
        "type": "leaf",
        "state": {
          "type": "bookmarks",
          "state": {}
        }
      }
    ],
    "currentTab": 0
  },
  "right": {
    "id": "672344c0e3009ae8",
    "type": "mobile-drawer",
    "children": [
      {
        "id": "c0f0c60e2267a735",
        "type": "leaf",
        "state": {
          "type": "backlink",
          "state": {
            "file": "006 References/ALevel-CS.pdf",
            "collapseAll": false,
            "extraContext": true,
            "sortOrder": "alphabetical",
            "showSearch": false,
            "searchQuery": "",
            "backlinkCollapsed": false,
            "unlinkedCollapsed": true
          }
        }
      },
      {
        "id": "f6c245fc2e8e1980",
        "type": "leaf",
        "state": {
          "type": "outgoing-link",
          "state": {
            "file": "006 References/ALevel-CS.pdf",
            "linksCollapsed": false,
            "unlinkedCollapsed": true
          }
        }
      },
      {
        "id": "f0dac29844fbf751",
        "type": "leaf",
        "state": {
          "type": "outline",
          "state": {
            "file": "006 References/ALevel-CS.pdf"
          }
        }
      },
      {
        "id": "e57b56fd06f6767b",
        "type": "leaf",
        "state": {
          "type": "calendar",
          "state": {}
        }
      },
      {
        "id": "abf7fbd5dea1172a",
        "type": "leaf",
        "state": {
          "type": "review-queue-list-view",
          "state": {}
        }
      },
      {
        "id": "237ca487dde87e64",
        "type": "leaf",
        "state": {
          "type": "reminder-list",
          "state": {}
        }
      }
    ],
    "currentTab": 0
  },
  "left-ribbon": {
    "hiddenItems": {
      "obsidian-omnivore:Omnivore": false,
      "zk-prefixer:Create new unique note": false,
      "random-note:Open random note": false,
      "switcher:Open quick switcher": false,
      "graph:Open graph view": false,
      "canvas:Create new canvas": false,
      "daily-notes:Open today's daily note": false,
      "templates:Insert template": false,
      "command-palette:Open command palette": false,
      "obsidian-excalidraw-plugin:Create new drawing": false,
      "table-editor-obsidian:Advanced Tables Toolbar": false,
      "obsidian-projects:Open projects": false,
      "omnisearch:Omnisearch": false,
      "obsidian-day-planner:Timeline": false
    }
  },
  "active": "e8acf4099b7af3fd",
  "lastOpenFiles": [
    "009 Canvasses/Untitled.canvas",
    "003 Literature/Longest Increasing Subsequence in O(nlogn) - LeetCode - Algorithm Explanation by alGOds!!.md",
    "003 Literature/permutations.md",
    "003 Literature/Availability — LessWrong.md",
    "003 Literature/The Martial Art of Rationality — LessWrong.md",
    "003 Literature/Scope Insensitivity — LessWrong.md",
    "003 Literature/Biases- An Introduction — LessWrong.md",
    "003 Literature/Private Conversation — LessWrong.md",
    "003 Literature/Concepts Portal — LessWrong.md",
    "003 Literature/Omnivore.md",
    "003 Literature/Rationality- A-Z — LessWrong.md",
    "003 Literature/ALevel-Phy.md",
    "Symbols.md",
    "003 Literature/The Secret Power of ‘Read It Later’ Apps.md",
    "003 Literature/Getting Started with Omnivore.md",
    "003 Literature/Organize your Omnivore library with labels.md",
    "003 Literature/2024-01-29/The Secret Power of ‘Read It Later’ Apps.md",
    "003 Literature/2024-01-29/Getting Started with Omnivore.md",
    "003 Literature/2024-01-29/Organize your Omnivore library with labels.md",
    "003 Literature/2024-01-29",
    "009 Canvasses",
    "005 References/Scott Alexander - Unsong.epub",
    "005 References/Harry Potter and the Methods of Rationality.pdf",
    "005 References/hpmor.pdf",
    "006 Templates",
    "005 References",
    "004 Daily",
    "003 Literature",
    "002 Fleeting"
  ]
}